versioning/__init__.py
versioning/__main__.py
versioning/changelog.py
versioning/cli.py
versioning/config.py
versioning/controller.py
versioning/exception.py
versioning/py.typed
versioning/vcs.py
versioning/version.py
versioning/grammars/__init__.py
versioning/grammars/conventional_commits.lark
versioning/grammars/conventional_commits.py
proman_versioning-0.7.1a1.dist-info/LICENSE.md
proman_versioning-0.7.1a1.dist-info/METADATA
proman_versioning-0.7.1a1.dist-info/WHEEL
proman_versioning-0.7.1a1.dist-info/entry_points.txt
proman_versioning-0.7.1a1.dist-info/top_level.txt
proman_versioning-0.7.1a1.dist-info/RECORD
